AUTHORS.rst
CONTRIBUTING.rst
HISTORY.rst
LICENSE
MANIFEST.in
README.rst
setup.cfg
setup.py
diablo3api/__init__.py
diablo3api/client.py
diablo3api/resources.py
diablo3api.egg-info/PKG-INFO
diablo3api.egg-info/SOURCES.txt
diablo3api.egg-info/dependency_links.txt
diablo3api.egg-info/not-zip-safe
diablo3api.egg-info/requires.txt
diablo3api.egg-info/top_level.txt
docs/Makefile
docs/authors.rst
docs/conf.py
docs/contributing.rst
docs/diablo3api.rst
docs/history.rst
docs/index.rst
docs/installation.rst
docs/make.bat
docs/modules.rst
docs/readme.rst
docs/resources.rst
docs/usage.rst
tests/__init__.py
tests/test_response.py
tests/test_url.py