Metadata-Version: 1.1
Name: diablo3api
Version: 0.1.0
Summary: A Python API Wrapper for the Diablo 3 API
Home-page: https://github.com/menglewis/diablo3api
Author: David Lewis
Author-email: meng.lewis@gmail.com
License: BSD
Keywords: diablo3api
Platform: UNKNOWN
Classifier: Development Status :: 2 - Pre-Alpha
Classifier: Intended Audience :: Developers
Classifier: License :: OSI Approved :: BSD License
Classifier: Natural Language :: English
Classifier: Programming Language :: Python :: 2
Classifier: Programming Language :: Python :: 2.6
Classifier: Programming Language :: Python :: 2.7
Classifier: Programming Language :: Python :: 3
Classifier: Programming Language :: Python :: 3.3
Classifier: Programming Language :: Python :: 3.4
